tsfx-0.2.0.dist-info/METADATA
tsfx-0.2.0.dist-info/WHEEL
tsfx-0.2.0.dist-info/licenses/LICENSE
tsfx.libs/libgcc_s-39080030.so.1
tsfx/__init__.py
tsfx/_tsfx.py
tsfx/py.typed
tsfx/tsfx.pyi
tsfx/tsfx.pypy39-pp73-aarch64-linux-gnu.so
tsfx-0.2.0.dist-info/RECORD
